{
  "id": "35c43e25-30ad-4467-b52a-f0b9e69121ed",
  "prevId": "81844708-9485-47eb-8e79-595a77dd48fd",
  "version": "7",
  "dialect": "postgresql",
  "tables": {
    "public.critter_profiles": {
      "name": "critter_profiles",
      "schema": "",
      "columns": {
        "id": {
          "name": "id",
          "type": "uuid",
          "primaryKey": true,
          "notNull": true,
          "default": "gen_random_uuid()"
        },
        "emoji": {
          "name": "emoji",
          "type": "text",
          "primaryKey": false,
          "notNull": true
        },
        "name": {
          "name": "name",
          "type": "text",
          "primaryKey": false,
          "notNull": true
        },
        "place": {
          "name": "place",
          "type": "text",
          "primaryKey": false,
          "notNull": false
        },
        "created_at": {
          "name": "created_at",
          "type": "timestamp with time zone",
          "primaryKey": false,
          "notNull": true,
          "default": "now()"
        }
      },
      "indexes": {},
      "foreignKeys": {},
      "compositePrimaryKeys": {},
      "uniqueConstraints": {},
      "policies": {},
      "checkConstraints": {},
      "isRLSEnabled": false
    },
    "public.emoji_requests": {
      "name": "emoji_requests",
      "schema": "",
      "columns": {
        "id": {
          "name": "id",
          "type": "uuid",
          "primaryKey": true,
          "notNull": true,
          "default": "gen_random_uuid()"
        },
        "name": {
          "name": "name",
          "type": "text",
          "primaryKey": false,
          "notNull": true
        },
        "note": {
          "name": "note",
          "type": "text",
          "primaryKey": false,
          "notNull": false
        },
        "created_at": {
          "name": "created_at",
          "type": "timestamp with time zone",
          "primaryKey": false,
          "notNull": true,
          "default": "now()"
        },
        "handled_at": {
          "name": "handled_at",
          "type": "timestamp with time zone",
          "primaryKey": false,
          "notNull": false
        },
        "pr_url": {
          "name": "pr_url",
          "type": "text",
          "primaryKey": false,
          "notNull": false
        },
        "outcome": {
          "name": "outcome",
          "type": "text",
          "primaryKey": false,
          "notNull": false
        }
      },
      "indexes": {},
      "foreignKeys": {},
      "compositePrimaryKeys": {},
      "uniqueConstraints": {},
      "policies": {},
      "checkConstraints": {},
      "isRLSEnabled": false
    },
    "public.push_subscriptions": {
      "name": "push_subscriptions",
      "schema": "",
      "columns": {
        "id": {
          "name": "id",
          "type": "uuid",
          "primaryKey": true,
          "notNull": true,
          "default": "gen_random_uuid()"
        },
        "endpoint": {
          "name": "endpoint",
          "type": "text",
          "primaryKey": false,
          "notNull": true
        },
        "p256dh": {
          "name": "p256dh",
          "type": "text",
          "primaryKey": false,
          "notNull": true
        },
        "auth": {
          "name": "auth",
          "type": "text",
          "primaryKey": false,
          "notNull": true
        },
        "created_at": {
          "name": "created_at",
          "type": "timestamp with time zone",
          "primaryKey": false,
          "notNull": true,
          "default": "now()"
        }
      },
      "indexes": {},
      "foreignKeys": {},
      "compositePrimaryKeys": {},
      "uniqueConstraints": {
        "push_subscriptions_endpoint_unique": {
          "name": "push_subscriptions_endpoint_unique",
          "nullsNotDistinct": false,
          "columns": [
            "endpoint"
          ]
        }
      },
      "policies": {},
      "checkConstraints": {},
      "isRLSEnabled": false
    },
    "public.sighting_likes": {
      "name": "sighting_likes",
      "schema": "",
      "columns": {
        "id": {
          "name": "id",
          "type": "uuid",
          "primaryKey": true,
          "notNull": true,
          "default": "gen_random_uuid()"
        },
        "sighting_id": {
          "name": "sighting_id",
          "type": "uuid",
          "primaryKey": false,
          "notNull": true
        },
        "device_id": {
          "name": "device_id",
          "type": "text",
          "primaryKey": false,
          "notNull": true
        },
        "created_at": {
          "name": "created_at",
          "type": "timestamp with time zone",
          "primaryKey": false,
          "notNull": true,
          "default": "now()"
        }
      },
      "indexes": {},
      "foreignKeys": {
        "sighting_likes_sighting_id_sightings_id_fk": {
          "name": "sighting_likes_sighting_id_sightings_id_fk",
          "tableFrom": "sighting_likes",
          "tableTo": "sightings",
          "columnsFrom": [
            "sighting_id"
          ],
          "columnsTo": [
            "id"
          ],
          "onDelete": "cascade",
          "onUpdate": "no action"
        }
      },
      "compositePrimaryKeys": {},
      "uniqueConstraints": {
        "sighting_likes_sighting_device": {
          "name": "sighting_likes_sighting_device",
          "nullsNotDistinct": false,
          "columns": [
            "sighting_id",
            "device_id"
          ]
        }
      },
      "policies": {},
      "checkConstraints": {},
      "isRLSEnabled": false
    },
    "public.sightings": {
      "name": "sightings",
      "schema": "",
      "columns": {
        "id": {
          "name": "id",
          "type": "uuid",
          "primaryKey": true,
          "notNull": true,
          "default": "gen_random_uuid()"
        },
        "emoji": {
          "name": "emoji",
          "type": "text",
          "primaryKey": false,
          "notNull": true
        },
        "name": {
          "name": "name",
          "type": "text",
          "primaryKey": false,
          "notNull": false
        },
        "sighted_on": {
          "name": "sighted_on",
          "type": "date",
          "primaryKey": false,
          "notNull": true
        },
        "sighted_time": {
          "name": "sighted_time",
          "type": "text",
          "primaryKey": false,
          "notNull": false
        },
        "place": {
          "name": "place",
          "type": "text",
          "primaryKey": false,
          "notNull": false
        },
        "comment": {
          "name": "comment",
          "type": "text",
          "primaryKey": false,
          "notNull": false
        },
        "quantity": {
          "name": "quantity",
          "type": "text",
          "primaryKey": false,
          "notNull": true,
          "default": "'1'"
        },
        "photo_path": {
          "name": "photo_path",
          "type": "text",
          "primaryKey": false,
          "notNull": false
        },
        "created_at": {
          "name": "created_at",
          "type": "timestamp with time zone",
          "primaryKey": false,
          "notNull": true,
          "default": "now()"
        }
      },
      "indexes": {},
      "foreignKeys": {},
      "compositePrimaryKeys": {},
      "uniqueConstraints": {},
      "policies": {},
      "checkConstraints": {},
      "isRLSEnabled": false
    }
  },
  "enums": {},
  "schemas": {},
  "sequences": {},
  "roles": {},
  "policies": {},
  "views": {},
  "_meta": {
    "columns": {},
    "schemas": {},
    "tables": {}
  }
}